octopipes/__init__.py
octopipes/aggregate_flows.py
octopipes/benchmark.py
octopipes/dataset.py
octopipes/handlers.py
octopipes/process.py
octopipes/process_debuging.py
octopipes/results.py
octopipes/utils.py
octopipes/workflow.py
octopipes/hooks/__init__.py
octopipes/hooks/pytorch_hooks.py
octopipes-0.2.5.dist-info/LICENSE
octopipes-0.2.5.dist-info/METADATA
octopipes-0.2.5.dist-info/WHEEL
octopipes-0.2.5.dist-info/top_level.txt
octopipes-0.2.5.dist-info/RECORD
