Metadata-Version: 2.1
Name: octopipes
Version: 0.2.5
Summary: Pipeline library for AI workflows.
Home-page: https://github.com/octomiro/octopipes
Author: Octomiro
Author-email: contact@octomiro.ai
Classifier: Programming Language :: Python :: 3.11
Classifier: Programming Language :: Python :: 3.10
Classifier: License :: OSI Approved :: MIT License
License-File: LICENSE
Requires-Dist: pydantic
Requires-Dist: multiprocess
Requires-Dist: numpy
Requires-Dist: tqdm
Requires-Dist: cmap
Provides-Extra: opencv
Requires-Dist: opencv-python ; extra == 'opencv'
Provides-Extra: pytorch
Requires-Dist: torch ; extra == 'pytorch'
Requires-Dist: torchvision ; extra == 'pytorch'
